greetmeee/__init__.py
greetmeee/test.py
greetmeee-0.0.3.dist-info/METADATA
greetmeee-0.0.3.dist-info/WHEEL
greetmeee-0.0.3.dist-info/top_level.txt
greetmeee-0.0.3.dist-info/RECORD
