Metadata-Version: 2.1
Name: greetmeee
Version: 0.0.3
Summary: Basic Greet Package
Author: Haseeb
Author-email: haseebasif5@gmail.com
Keywords: python,greet,greetmeee,greetmeee package
Classifier: Development Status :: 1 - Planning
Classifier: Intended Audience :: Developers
Classifier: Programming Language :: Python :: 3
Classifier: Operating System :: Unix
Classifier: Operating System :: MacOS :: MacOS X
Classifier: Operating System :: Microsoft :: Windows
